alu.v
module alu (
    input [3:0] A, B,
    input [2:0] ALU_Sel,
    output reg [3:0] ALU_Out,
    output reg CarryOut
);

always @(*) begin
    case (ALU_Sel)
        3'b000: {CarryOut, ALU_Out} = A + B;   // Addition
        3'b001: {CarryOut, ALU_Out} = A - B;   // Subtraction
        3'b010: ALU_Out = A & B;               // AND
        3'b011: ALU_Out = A | B;               // OR
        3'b100: ALU_Out = A ^ B;               // XOR
        3'b101: ALU_Out = ~A;                  // NOT
        3'b110: ALU_Out = A << 1;              // Shift left
        3'b111: ALU_Out = A >> 1;              // Shift right
        default: ALU_Out = 4'b0000;
    endcase
end

endmodule

alu_tb.v
`timescale 1ns/1ps
module alu_tb;

reg [3:0] A, B;
reg [2:0] ALU_Sel;
wire [3:0] ALU_Out;
wire CarryOut;

// Instantiate ALU
alu uut (
    .A(A), .B(B), .ALU_Sel(ALU_Sel),
    .ALU_Out(ALU_Out), .CarryOut(CarryOut)
);

initial begin
    $dumpfile("alu.vcd");   // waveform output
    $dumpvars(0, alu_tb);

    // Test cases
    A = 4'b0011; B = 4'b0001; ALU_Sel = 3'b000; #10; // 3+1
    A = 4'b0100; B = 4'b0010; ALU_Sel = 3'b001; #10; // 4-2
    A = 4'b1010; B = 4'b1100; ALU_Sel = 3'b010; #10; // AND
    A = 4'b1010; B = 4'b1100; ALU_Sel = 3'b011; #10; // OR
    A = 4'b1010; B = 4'b1100; ALU_Sel = 3'b100; #10; // XOR
    A = 4'b1010; B = 4'b0000; ALU_Sel = 3'b101; #10; // NOT
    A = 4'b1010; B = 4'b0000; ALU_Sel = 3'b110; #10; // Shift left
    A = 4'b1010; B = 4'b0000; ALU_Sel = 3'b111; #10; // Shift right

    $finish;
end

endmodule

alu.vcd
$date
	Tue Sep 16 17:52:06 2025
$end
$version
	Icarus Verilog
$end
$timescale
	1ps
$end
$scope module alu_tb $end
$var wire 1 ! CarryOut $end
$var wire 4 " ALU_Out [3:0] $end
$var reg 4 # A [3:0] $end
$var reg 3 $ ALU_Sel [2:0] $end
$var reg 4 % B [3:0] $end
$scope module uut $end
$var wire 4 & A [3:0] $end
$var wire 3 ' ALU_Sel [2:0] $end
$var wire 4 ( B [3:0] $end
$var reg 4 ) ALU_Out [3:0] $end
$var reg 1 ! CarryOut $end
$upscope $end
$upscope $end
$enddefinitions $end
$comment Show the parameter values. $end
$dumpall
$end
#0
$dumpvars
b100 )
b1 (
b0 '
b11 &
b1 %
b0 $
b11 #
b100 "
0!
$end
#10000
b10 "
b10 )
b1 $
b1 '
b10 %
b10 (
b100 #
b100 &
#20000
b1000 "
b1000 )
b10 $
b10 '
b1100 %
b1100 (
b1010 #
b1010 &
#30000
b1110 "
b1110 )
b11 $
b11 '
#40000
b110 "
b110 )
b100 $
b100 '
#50000
b101 "
b101 )
b101 $
b101 '
b0 %
b0 (
#60000
b100 "
b100 )
b110 $
b110 '
#70000
b101 "
b101 )
b111 $
b111 '
